LICENSE
MANIFEST.in
README.rst
setup.cfg
setup.py
fastapi_common_question/__init__.py
fastapi_common_question/api/__init__.py
fastapi_common_question/api/deps.py
fastapi_common_question/api/api_v1/__init__.py
fastapi_common_question/api/api_v1/endpoints/__init__.py
fastapi_common_question/api/api_v1/endpoints/common_question.py
fastapi_common_question/crud/__init__.py
fastapi_common_question/crud/base.py
fastapi_common_question/crud/crud.py
fastapi_common_question/crud/crud_common_question.py
fastapi_common_question/exceptions/__init__.py
fastapi_common_question/exceptions/base_exception.py
fastapi_common_question/exceptions/public_exceptions.py
fastapi_common_question/exceptions/util_exception.py
fastapi_common_question/filters/__init__.py
fastapi_common_question/filters/base_filter.py
fastapi_common_question/filters/common_question_filter.py
fastapi_common_question/models/__init__.py
fastapi_common_question/models/common_question.py
fastapi_common_question/models/models.py
fastapi_common_question/orders/__init__.py
fastapi_common_question/orders/base_order.py
fastapi_common_question/schemas/__init__.py
fastapi_common_question/schemas/base.py
fastapi_common_question/schemas/common_question.py
fastapi_common_question/schemas/schemas.py
fastapi_common_questions.egg-info/PKG-INFO
fastapi_common_questions.egg-info/SOURCES.txt
fastapi_common_questions.egg-info/dependency_links.txt
fastapi_common_questions.egg-info/requires.txt
fastapi_common_questions.egg-info/top_level.txt