Metadata-Version: 2.1
Name: fastapi-common-questions
Version: 0.1
Summary: A Fast api module to conduct Web-based common question.
Home-page: https://example.com/
Author: Haydar Ghasemi
Author-email: Haydar.Ghasemi@gmail.com
License: BSD-3-Clause  # Example license
Platform: UNKNOWN
Classifier: Intended Audience :: Developers
Classifier: License :: OSI Approved :: BSD License
Classifier: Operating System :: OS Independent
Classifier: Programming Language :: Python
Classifier: Programming Language :: Python :: 3
Classifier: Programming Language :: Python :: 3 :: Only
Classifier: Programming Language :: Python :: 3.6
Classifier: Programming Language :: Python :: 3.7
Classifier: Programming Language :: Python :: 3.8
Classifier: Topic :: Internet :: WWW/HTTP
Classifier: Topic :: Internet :: WWW/HTTP :: Dynamic Content
Requires-Python: >=3.6
License-File: LICENSE
